deep_research/__init__.py
deep_research/core/__init__.py
deep_research/core/callbacks.py
deep_research/models/__init__.py
deep_research/models/models.py
deep_research/utils/__init__.py
deep_research/utils/base_client.py
deep_research/utils/docling_client.py
deep_research/utils/docling_client_models.py
deep_research/utils/docling_server_client.py
deep_research/utils/firecrawl_client.py
deep_research/utils/cache/__init__.py
deep_research/utils/cache/cache_decorator.py
deep_research/utils/cache/cache_models.py
deep_research/utils/web/__init__.py
deep_research/utils/web/base_search.py
deep_research/utils/web/brave_search.py
deep_research/utils/web/duckduckgo_search.py
deep_research/utils/web/search_provider.py
deep_research_sdk-0.1.2.dist-info/licenses/LICENSE
deep_research_sdk-0.1.2.dist-info/METADATA
deep_research_sdk-0.1.2.dist-info/WHEEL
deep_research_sdk-0.1.2.dist-info/top_level.txt
deep_research_sdk-0.1.2.dist-info/RECORD
