Metadata-Version: 2.4
Name: deep-research-sdk
Version: 0.1.2
Summary: Python SDK for Open Deep Research
Requires-Python: <4.0,>=3.11
License-File: LICENSE
Requires-Dist: pydantic>=2.11.1
Requires-Dist: aiohttp>=3.8.0
Requires-Dist: duckduckgo-search>=8.0.0
Requires-Dist: requests>=2.32.3
Requires-Dist: sqlmodel>=0.0.16
Requires-Dist: tokenizers>=0.21.1
Requires-Dist: litellm>=1.65.1
Requires-Dist: docling>=2.15.1
Dynamic: license-file
